rae_dle/__init__.py
rae_dle/rae.py
rae_dle-0.1.0.dist-info/WHEEL
rae_dle-0.1.0.dist-info/METADATA
rae_dle-0.1.0.dist-info/RECORD
