Metadata-Version: 2.1
Name: rae-dle
Version: 0.1.0
Summary: 
Author: Pedro Sanchez
Author-email: pedrosanchez757@hotmail.com
Requires-Python: >=3.9,<4.0
Classifier: Programming Language :: Python :: 3
Classifier: Programming Language :: Python :: 3.10
Classifier: Programming Language :: Python :: 3.9
Requires-Dist: selenium (>=4.1.0,<5.0.0)
